malt/__init__.py
malt/__main__.py
malt/bounding_object_cache.py
malt/image_manager.py
malt/main.py
malt/movable_objects.py
malt/object_detector.py
malt/video_manager.py
malt/py_ui/__init__.py
malt/py_ui/ui_core_window.py
maltk-0.0.0.1.dist-info/LICENSE
maltk-0.0.0.1.dist-info/METADATA
maltk-0.0.0.1.dist-info/WHEEL
maltk-0.0.0.1.dist-info/entry_points.txt
maltk-0.0.0.1.dist-info/top_level.txt
maltk-0.0.0.1.dist-info/RECORD
