Metadata-Version: 2.1
Name: maltk
Version: 0.0.0.1
Summary: Model Assisted Object Labeling Toolkit
Author: Matthew Sessions
License: UNKNOWN
Keywords: tensorflow,object detection,object labeling,image labeler,model assisted labeling,video to image
Platform: UNKNOWN
License-File: LICENSE
Requires-Dist: PySide6
Requires-Dist: tflite-support (>=0.4.3)
Requires-Dist: pascal-voc-writer
Requires-Dist: opencv-python
